{
    "article": "France 2 recrute une remplaçante de luxe. Selon la chaîne publique, le samedi 4 novembre prochain, Claire Chazal prendra place aux côtés de Yann Moix pour cuisiner les invités de l'émission hebdomadaire \"On n'est pas couché\". Elle suppléera donc Christine Angot qui sera alors en déplacement aux États-Unis dans le cadre de la promotion d'un de ses livres. Pas de sanction, donc, pour la chroniqueuse si décriée, malgré des audiences en berne depuis la rentrée et une ardente polémique à la suite d'un affrontement verbal avec Sandrine Rousseau, le 30 septembre dernier. De son côté, Claire Chazal, évincée du 20h de TF1 en septembre 2015, avait rapidement pu exercer à nouveau son talent, notamment avec la présentation de l'émission \"Entrée libre\", sur France 5, dont elle s'occupe depuis janvier 2016.",
    "date": "2017-10-16",
    "heading": "",
    "title": "\"On n'est pas couché\" : Claire Chazal à la place de Christine Angot"
}