{
    "article": "La députée européenne n'a toujours pas digéré ce qu'elle appelle un \"échec cuisant\". \"On le paie cher aujourd'hui. On paie quoi ? L'opacité et le mensonge, pour quelqu'un qui, rappelez-vous, avait dit : \"Qui aurait pu imaginer le général de Gaulle mis en examen ?\". Voilà, nous sommes les dégâts collatéraux de l'opacité et du mensonge de M. Fillon\", a déclaré Rachida Dati sur BFMTV. Elle regrette que son camp n'ait pas \"poussé\" assez fort pour que François Fillon change d'avis et décide de se retirer.",
    "date": "2018-01-28",
    "heading": "Elle considère que cette élection devait être gagnée par la droite \"sans faire campagne\", et pourtant les affaires de François Fillon auront eu raison de ce projet. Alors que le Conseil national des Républicains vient de se réunir en pleine division de la droite, Rachida Dati a estimé dimanche 28 janvier sur BFMTV que le principal responsable de la situation est le candidat malheureux à l'élection présidentielle.",
    "title": "\"Opacité\", \"mensonge\" : pour Rachida Dati, la droite est victime de François Fillon"
}