{
    "article": "QUI ? L'ancien Premier ministre a jugé, jeudi, le leader de la France insoumise (LFI) \"dangereux\" pour le pays. Le député de Seine-Saint-Denis lui répond vendredi, en étrillant son bilan. \"Qui est ce gugus pour nous parler comme ça ?\" : Alexis Corbière répond à Manuel Vallspar franceinfo Invité de BFMTV jeudi 21 septembre, Manuel Valls a critiqué Jean-Luc Mélenchon, le qualifiant d'\"adversaire politique (...) dangereux pour mon pays\". \"On ne se comporte pas comme un factieux, on est à un certain niveau\", a tancé le député de l'Essonne. Des mots qui font réagir, vendredi, Alexis Corbière. \"Au fou, au fou\", a lancé le député LFI de Seine-Saint-Denis sur France Info. \"C'est totalement déraisonnable. Ce qui a été dangereux pour le pays, ça a été la politique de Manuel Valls\", juge-t-il. Et de détailler : \"Il a quand même gouverné par le 49.3 (...). Il a explosé son parti : je lui rappelle que Solférino va être mis en vente grâce aux brillantes idées et au talent de Manuel Valls. Il est un député totalement absent : les gens qui ont voté pour lui à Évry, qu'ils sachent qu'ils ont un député qui ne fait rien, qui n'intervient jamais\", s'est emporté Alexis Corbière. \"Et ce monsieur sort de sa boîte pour dire quoi, quel est le problème du pays ? Jean-Luc Mélenchon ! Ridicule !\", juge-t-il. \"Qui c'est ce gugusse pour nous parler comme ça ? Qui il est, Manuel Valls ?\", a-t-il interrogé.",
    "date": "2017-09-22",
    "heading": "",
    "title": "VIDÉO. Corbière (La France insoumise) répond à Valls : \"Qui c'est, ce gugusse, pour nous parler comme ça ?\""
}